LICENSE
MANIFEST.in
Makefile
README.rst
requirements.txt
setup.cfg
setup.py
quorra/__init__.py
quorra/__main__.py
quorra/methods.py
quorra/models.py
quorra.egg-info/PKG-INFO
quorra.egg-info/SOURCES.txt
quorra.egg-info/dependency_links.txt
quorra.egg-info/not-zip-safe
quorra.egg-info/requires.txt
quorra.egg-info/top_level.txt
quorra/tmpl/export.html
quorra/tmpl/render.html
tests/__init__.py
tests/__init__.pyc
tests/test_quorra.py
tests/test_quorra.pyc
tests/tmp.py
tests/__pycache__/__init__.cpython-34.pyc
tests/__pycache__/test_quorra.cpython-34.pyc