Metadata-Version: 1.1
Name: quorra
Version: 0.0.8
Summary: A python extension for generating quorra.js plots directly from python
Home-page: https://github.com/bprinty/quorra
Author: Blake Printy
Author-email: bprinty@gmail.com
License: Apache-2.0
Keywords: quorra,visualization,plotting,charts,data
Platform: UNKNOWN
Classifier: Intended Audience :: Developers
Classifier: License :: OSI Approved :: Apple Public Source License
Classifier: Natural Language :: English
Classifier: Programming Language :: Python :: 2
Classifier: Programming Language :: Python :: 2.6
Classifier: Programming Language :: Python :: 2.7
Classifier: Programming Language :: Python :: 3
Classifier: Programming Language :: Python :: 3.3
Classifier: Programming Language :: Python :: 3.4
